{
  "action_name": "cicd_run_build",
  "active": true,
  "client": false,
  "comments": "Run CICD Process based on a Scoped Application",
  "condition": "(gs.getProperty('cicd-integration.enabled', 'false') == 'true' && gs.getProperty('cicd-integration.enabled.on-scoped-app', 'false') == 'true' && current.vendor != 'ServiceNow' && current.canWrite())",
  "form_action": true,
  "form_button": true,
  "form_context_menu": false,
  "form_link": false,
  "form_style": "",
  "hint": "",
  "list_action": false,
  "list_banner_button": false,
  "list_button": false,
  "list_choice": false,
  "list_context_menu": false,
  "list_link": false,
  "list_save_with_form_button": false,
  "list_style": "",
  "name": "Build this Application [CICD]",
  "onclick": "",
  "order": -1,
  "script": {
    "____see": "sn/CICD Integration/UI Action/sys_app/active_true/Build this Application [CICD].js"
  },
  "show_insert": false,
  "show_multiple_update": false,
  "show_query": false,
  "show_update": true,
  "sys_class_name": "sys_ui_action",
  "sys_created_by": "b.moers",
  "sys_created_on": "2019-02-05 15:23:32",
  "sys_customer_update": false,
  "sys_domain": "global",
  "sys_id": "3ee71f77db57a7801af8b14ffe9619c2",
  "sys_mod_count": 15,
  "sys_name": "Build this Application [CICD]",
  "sys_overrides": "",
  "sys_package": "19190fabdbebd300dfa9b94ffe96193e",
  "sys_policy": "",
  "sys_replace_on_upgrade": false,
  "sys_scope": "19190fabdbebd300dfa9b94ffe96193e",
  "sys_update_name": "sys_ui_action_3ee71f77db57a7801af8b14ffe9619c2",
  "sys_updated_by": "b.moers",
  "sys_updated_on": "2019-02-28 14:21:08",
  "table": "sys_app",
  "ui11_compatible": true,
  "ui16_compatible": false
}
